{"荣耀（HONOR）荣耀play4T":96,"小米Redmi Note9 Pro":96,"小米Redmi Note9 5G":97,"OPPOReno5 5G":96,"OPPOA93":97,"小米Redmi 9A":98,"三星Galaxy S21 5G":186,"小米Redmi 8A":97,"小米Redmi Note 9 4G":97,"小米Redmi Note8":97,"OPPOA52":96,"小米Redmi 9":98,"荣耀V40":190,"AppleiPhone 11":95,"小米Redmi K30":94,"vivoiQOO U1x":194,"OPPOK7x":96,"真我Q2":96,"vivoiQOO 7":190,"vivoiQOO Neo3":95,"AppleiPhone 12":94,"一加8T":95,"小米Redmi 10X 5G":96,"荣耀9X PRO":96,"锤子坚果R2":96,"小米Redmi 10X 4G":97,"vivoiQOO U1":97,"真我V15":96,"OPPOK7":95,"OPPOAce2":94,"华为（HUAWEI）Mate 40":99,"真我Q2 Pro":96,"AppleiPhone 12 Pro Max":96,"荣耀Play4T Pro":97,"OPPOA8":96,"天语（K-TOUCH）T12 Pro":97,"vivoiQOO U3":192,"OPPOReno5 Pro 5G":96,"华为Mate 40 Pro":98,"小米10":92,"小米（MI）小米红米9A":96,"小米 11":91,"OPPOReno5 Pro+":96,"AppleiPhone 12 Pro":97,"OPPO A8":96,"华为（HUAWEI）Mate 40 Pro":96,"荣耀30 Pro":96,"vivoY52s":97,"荣耀Play4T":97,"真我X7 Pro":94,"vivoX60 Pro":96,"OPPOReno4 SE":95,"OPPOReno5":96,"一加8":94,"三星Galaxy A71":92}